deepsemhist/__init__.py
deepsemhist/data.py
deepsemhist/patch.py
deepsemhist/predict.py
deepsemhist/segpatch.py
deepsemhist/segslide.py
deepsemhist/utils.py
deepsemhist/viz.py
deepsemhist/wsi_class.py
deepsemhist-0.0.3.dist-info/METADATA
deepsemhist-0.0.3.dist-info/WHEEL
deepsemhist-0.0.3.dist-info/entry_points.txt
deepsemhist-0.0.3.dist-info/top_level.txt
deepsemhist-0.0.3.dist-info/RECORD
