Metadata-Version: 2.1
Name: deepsemhist
Version: 0.0.3
Summary: deep_semantic_histology: Deep Semantic Representations for Cancer Histology Images
Home-page: https://github.com/dakomura/deep_texture_histology
Author: Daisuke Komura
Author-email: kdais-prm@m.u-tokyo.ac.jp
Maintainer: Daisuke Komura
Maintainer-email: kdais-prm@m.u-tokyo.ac.jp
License: CC-BY-NC-SA 4.0
Download-URL: https://github.com/dakomura/deep_texture_histology
Platform: UNKNOWN
Classifier: Intended Audience :: Science/Research
Classifier: License :: OSI Approved :: BSD License
Classifier: Programming Language :: Python :: 3
Classifier: Programming Language :: Python :: 3.6
Classifier: Programming Language :: Python :: 3.7
Classifier: Programming Language :: Python :: 3.8
Classifier: Programming Language :: Python :: 3.9
Classifier: Programming Language :: Python :: 3 :: Only
Classifier: Topic :: Scientific/Engineering
Classifier: Topic :: Scientific/Engineering :: Visualization
Classifier: Topic :: Scientific/Engineering :: Artificial Intelligence
Requires-Python: >=3.6
Requires-Dist: numpy
Requires-Dist: joblib
Requires-Dist: Pillow
Requires-Dist: matplotlib
Requires-Dist: seaborn
Requires-Dist: pandas
Requires-Dist: pyrsistent
